{"resource":"playercareerstats","parameters":{"PerMode":"PerGame","PlayerID":203518,"LeagueID":null},"resultSets":[{"name":"SeasonTotalsRegularSeason","headers":["PLAYER_ID","SEASON_ID","LEAGUE_ID","TEAM_ID","TEAM_ABBREVIATION","PLAYER_AGE","GP","GS","MIN","FGM","FGA","FG_PCT","FG3M","FG3A","FG3_PCT","FTM","FTA","FT_PCT","OREB","DREB","REB","AST","STL","BLK","TOV","PF","PTS"],"rowSet":[[203518,"2016-17","00",1610612760,"OKC",23,68,6,15.5,2,5,0.393,1.4,3.6,0.381,0.6,0.7,0.898,0.3,1,1.3,0.6,0.5,0.1,0.5,1.7,6],[203518,"2017-18","00",1610612760,"OKC",24,75,8,15.1,1.5,3.9,0.395,1.1,2.9,0.38,0.5,0.6,0.848,0.3,1.2,1.5,0.4,0.5,0.1,0.3,1.7,4.7],[203518,"2018-19","00",1610612760,"OKC",25,31,2,19,1.8,5.1,0.357,1.3,4.1,0.323,0.4,0.4,0.923,0.2,1.4,1.5,0.6,0.5,0.2,0.5,1.7,5.3]]},{"name":"CareerTotalsRegularSeason","headers":["PLAYER_ID","LEAGUE_ID","Team_ID","GP","GS","MIN","FGM","FGA","FG_PCT","FG3M","FG3A","FG3_PCT","FTM","FTA","FT_PCT","OREB","DREB","REB","AST","STL","BLK","TOV","PF","PTS"],"rowSet":[[203518,"00",0,174,16,16,1.8,4.5,0.387,1.3,3.4,0.368,0.5,0.6,0.88,0.3,1.1,1.4,0.5,0.5,0.1,0.4,1.7,5.3]]},{"name":"SeasonTotalsPostSeason","headers":["PLAYER_ID","SEASON_ID","LEAGUE_ID","TEAM_ID","TEAM_ABBREVIATION","PLAYER_AGE","GP","GS","MIN","FGM","FGA","FG_PCT","FG3M","FG3A","FG3_PCT","FTM","FTA","FT_PCT","OREB","DREB","REB","AST","STL","BLK","TOV","PF","PTS"],"rowSet":[[203518,"2016-17","00",1610612760,"OKC",23,5,0,16,1.6,4.6,0.348,1,3.4,0.294,0.6,0.8,0.75,0.4,1.4,1.8,0.8,0,0,0,1.6,4.8],[203518,"2017-18","00",1610612760,"OKC",24,6,0,18.3,1.3,3.3,0.4,1,2.2,0.462,0.3,0.3,1,0.5,2.2,2.7,0.3,0.8,0.3,0.2,1.8,4]]},{"name":"CareerTotalsPostSeason","headers":["PLAYER_ID","LEAGUE_ID","Team_ID","GP","GS","MIN","FGM","FGA","FG_PCT","FG3M","FG3A","FG3_PCT","FTM","FTA","FT_PCT","OREB","DREB","REB","AST","STL","BLK","TOV","PF","PTS"],"rowSet":[[203518,"00",0,11,0,17.3,1.5,3.9,0.372,1,2.7,0.367,0.5,0.5,0.833,0.5,1.8,2.3,0.5,0.5,0.2,0.1,1.7,4.4]]},{"name":"SeasonTotalsAllStarSeason","headers":["PLAYER_ID","SEASON_ID","LEAGUE_ID","TEAM_ID","TEAM_ABBREVIATION","PLAYER_AGE","GP","GS","MIN","FGM","FGA","FG_PCT","FG3M","FG3A","FG3_PCT","FTM","FTA","FT_PCT","OREB","DREB","REB","AST","STL","BLK","TOV","PF","PTS"],"rowSet":[]},{"name":"CareerTotalsAllStarSeason","headers":["PLAYER_ID","LEAGUE_ID","Team_ID","GP","GS","MIN","FGM","FGA","FG_PCT","FG3M","FG3A","FG3_PCT","FTM","FTA","FT_PCT","OREB","DREB","REB","AST","STL","BLK","TOV","PF","PTS"],"rowSet":[]},{"name":"SeasonTotalsCollegeSeason","headers":["PLAYER_ID","SEASON_ID","LEAGUE_ID","ORGANIZATION_ID","SCHOOL_NAME","PLAYER_AGE","GP","GS","MIN","FGM","FGA","FG_PCT","FG3M","FG3A","FG3_PCT","FTM","FTA","FT_PCT","OREB","DREB","REB","AST","STL","BLK","TOV","PF","PTS"],"rowSet":[]},{"name":"CareerTotalsCollegeSeason","headers":["PLAYER_ID","LEAGUE_ID","ORGANIZATION_ID","GP","GS","MIN","FGM","FGA","FG_PCT","FG3M","FG3A","FG3_PCT","FTM","FTA","FT_PCT","OREB","DREB","REB","AST","STL","BLK","TOV","PF","PTS"],"rowSet":[]},{"name":"SeasonTotalsShowcaseSeason","headers":["PLAYER_ID","SEASON_ID","LEAGUE_ID","TEAM_ID","TEAM_ABBREVIATION","PLAYER_AGE","GP","GS","MIN","FGM","FGA","FG_PCT","FG3M","FG3A","FG3_PCT","FTM","FTA","FT_PCT","OREB","DREB","REB","AST","STL","BLK","TOV","PF","PTS"],"rowSet":[]},{"name":"CareerTotalsShowcaseSeason","headers":["PLAYER_ID","LEAGUE_ID","Team_ID","GP","GS","MIN","FGM","FGA","FG_PCT","FG3M","FG3A","FG3_PCT","FTM","FTA","FT_PCT","OREB","DREB","REB","AST","STL","BLK","TOV","PF","PTS"],"rowSet":[]},{"name":"SeasonRankingsRegularSeason","headers":["PLAYER_ID","SEASON_ID","LEAGUE_ID","TEAM_ID","TEAM_ABBREVIATION","PLAYER_AGE","GP","GS","RANK_PG_MIN","RANK_PG_FGM","RANK_PG_FGA","RANK_FG_PCT","RANK_PG_FG3M","RANK_PG_FG3A","RANK_FG3_PCT","RANK_PG_FTM","RANK_PG_FTA","RANK_FT_PCT","RANK_PG_OREB","RANK_PG_DREB","RANK_PG_REB","RANK_PG_AST","RANK_PG_STL","RANK_PG_BLK","RANK_PG_TOV","RANK_PG_PTS","RANK_PG_EFF"],"rowSet":[[203518,"2016-17","00",1610612760,"OKC","NR","NR","NR",248,242,242,null,84,84,45,225,225,null,247,269,269,253,192,240,261,228,262],[203518,"2017-18","00",1610612760,"OKC","NR","NR","NR",234,238,238,null,116,116,55,228,228,null,213,247,246,250,192,236,251,234,248],[203518,"2018-19","00",1610612760,"OKC","NR","NR","NR",null,null,null,null,null,null,null,null,null,null,null,null,null,null,null,null,null,null,null]]},{"name":"SeasonRankingsPostSeason","headers":["PLAYER_ID","SEASON_ID","LEAGUE_ID","TEAM_ID","TEAM_ABBREVIATION","PLAYER_AGE","GP","GS","RANK_PG_MIN","RANK_PG_FGM","RANK_PG_FGA","RANK_FG_PCT","RANK_PG_FG3M","RANK_PG_FG3A","RANK_FG3_PCT","RANK_PG_FTM","RANK_PG_FTA","RANK_FT_PCT","RANK_PG_OREB","RANK_PG_DREB","RANK_PG_REB","RANK_PG_AST","RANK_PG_STL","RANK_PG_BLK","RANK_PG_TOV","RANK_PG_PTS","RANK_PG_EFF"],"rowSet":[[203518,"2016-17","00",1610612760,"OKC","NR","NR","NR",112,125,125,null,63,63,60,114,114,null,107,124,127,109,146,127,151,120,133],[203518,"2017-18","00",1610612760,"OKC","NR","NR","NR",null,null,null,null,null,null,null,null,null,null,null,null,null,null,null,null,null,null,null]]}]}